<Properties GitUserInfo="UsingGIT" StartupConfiguration="{7475057A-CEC4-46DA-9D2F-D24A2B88CC48}|Default">
  <MonoDevelop.Ide.Workbench ActiveDocument="Controllers/API/V1/APIController.cs">
    <Files>
      <File FileName="Program.cs" Line="25" Column="1" />
      <File FileName="Controllers/DeveloperController.cs" Line="187" Column="43" />
      <File FileName="Services/Authentication/AuthenticationService.cs" Line="14" Column="36" />
      <File FileName="Services/DAL/Developer/DeveloperAccountsService.cs" Line="40" Column="2" />
      <File FileName="Startup.cs" Line="1" Column="1" />
      <File FileName="appsettings.json" Line="18" Column="30" />
      <File FileName="appsettings.Development.json" Line="10" Column="1" />
      <File FileName="Views/Shared/_Layout.cshtml" Line="16" Column="48" />
      <File FileName="Controllers/ApplicationController.cs" Line="121" Column="48" />
      <File FileName="Views/Shared/_ValidationScriptsPartial.cshtml" Line="1" Column="1" />
      <File FileName="Controllers/API/V1/APIController.cs" Line="1" Column="1" />
    </Files>
    <Pads>
      <Pad Id="ProjectPad">
        <State name="__root__">
          <Node name="shrtlnk" expanded="True">
            <Node name="shrtlnk" expanded="True">
              <Node name="Controllers" expanded="True">
                <Node name="API" expanded="True">
                  <Node name="V1" expanded="True">
                    <Node name="APIController.cs" selected="True" />
                  </Node>
                  <Node name="V2" expanded="True" />
                </Node>
              </Node>
              <Node name="Models" expanded="True">
                <Node name="Developer" expanded="True">
                  <Node name="DTO" expanded="True" />
                </Node>
                <Node name="Objects" expanded="True" />
              </Node>
              <Node name="Services" expanded="True">
                <Node name="API" expanded="True" />
                <Node name="Applications" expanded="True" />
                <Node name="Authentication" expanded="True" />
                <Node name="DAL" expanded="True">
                  <Node name="Application" expanded="True" />
                  <Node name="Developer" expanded="True" />
                </Node>
              </Node>
              <Node name="Views" expanded="True">
                <Node name="Application" expanded="True" />
                <Node name="Developer" expanded="True" />
                <Node name="Home" expanded="True" />
                <Node name="Shared" expanded="True" />
              </Node>
              <Node name="wwwroot" expanded="True">
                <Node name="css" expanded="True">
                  <Node name="Application" expanded="True" />
                </Node>
                <Node name="lib" expanded="True">
                  <Node name="bootstrap" expanded="True">
                    <Node name="dist" expanded="True">
                      <Node name="css" expanded="True" />
                    </Node>
                  </Node>
                </Node>
              </Node>
              <Node name="appsettings.json" expanded="True" />
            </Node>
          </Node>
        </State>
      </Pad>
      <Pad Id="MonoDevelop.Debugger.WatchPad">
        <State />
      </Pad>
    </Pads>
  </MonoDevelop.Ide.Workbench>
  <MonoDevelop.Ide.DebuggingService.PinnedWatches />
  <MonoDevelop.Ide.Workspace ActiveConfiguration="Debug" />
  <MonoDevelop.Ide.ItemProperties.shrtlnk PreferredExecutionTarget="/Applications/Google Chrome.app" />
  <MonoDevelop.Ide.DebuggingService.Breakpoints>
    <BreakpointStore />
  </MonoDevelop.Ide.DebuggingService.Breakpoints>
  <MultiItemStartupConfigurations />
</Properties>